pyvol_terminal/__init__.py
pyvol_terminal/application copy.py
pyvol_terminal/defaults.py
pyvol_terminal/exceptions.py
pyvol_terminal/gui_window2222.py
pyvol_terminal/init_warnings.py
pyvol_terminal/metric_attributes.py
pyvol_terminal/misc_classes.py
pyvol_terminal/misc_widgets.py
pyvol_terminal/requirements_tracker.py
pyvol_terminal/ui_themes.py
pyvol_terminal/utils.py
pyvol_terminal/windows copy.py
pyvol_terminal/windows.py
pyvol_terminal/workers copy.py
pyvol_terminal/workers.py
pyvol_terminal/data_classes/builders copy.py
pyvol_terminal/data_classes/builders.py
pyvol_terminal/data_classes/builders2.py
pyvol_terminal/data_classes/classes.py
pyvol_terminal/data_classes/classes_old.py
pyvol_terminal/data_classes/containers.py
pyvol_terminal/data_classes/old/classes2.py
pyvol_terminal/data_classes/old/classes3.py
pyvol_terminal/data_classes/old/utils2.py
pyvol_terminal/engines/__init__.py
pyvol_terminal/engines/interpolation_engines.py
pyvol_terminal/engines/surface_engines.py
pyvol_terminal/engines/option_engines/base.py
pyvol_terminal/engines/option_engines/black.py
pyvol_terminal/engines/option_engines/black_scholes_merton.py
pyvol_terminal/engines/option_engines/interpolation.py
pyvol_terminal/engines/yield_engines/__init__.py
pyvol_terminal/engines/yield_engines/implied_engines.py
pyvol_terminal/gl_3D_graphing/__init__.py
pyvol_terminal/gl_3D_graphing/meta.py
pyvol_terminal/gl_3D_graphing/utils.py
pyvol_terminal/gl_3D_graphing/graphics_items/AbstractGLGraphicsItem.py
pyvol_terminal/gl_3D_graphing/graphics_items/AbstractGLPlotItem copy 2.py
pyvol_terminal/gl_3D_graphing/graphics_items/AbstractGLPlotItem.py
pyvol_terminal/gl_3D_graphing/graphics_items/BaseGLLinePlotItem.py
pyvol_terminal/gl_3D_graphing/graphics_items/GL3DAxisItem.py
pyvol_terminal/gl_3D_graphing/graphics_items/GL3DGraphicsItemMixin copy.py
pyvol_terminal/gl_3D_graphing/graphics_items/GL3DGraphicsItemMixin.py
pyvol_terminal/gl_3D_graphing/graphics_items/GL3DGraphicsItems.py
pyvol_terminal-0.0.1.dist-info/METADATA
pyvol_terminal-0.0.1.dist-info/WHEEL
pyvol_terminal-0.0.1.dist-info/top_level.txt
pyvol_terminal-0.0.1.dist-info/RECORD
