Metadata-Version: 2.4
Name: pyvol-terminal
Version: 0.0.1
Summary: A package that generates a terminal for display realtime volatility analytics
Author-email: Ted Love <tedlove@victoriarivertrading.com>
Requires-Python: >=3.13
Requires-Dist: nest-asyncio>=1.6.0
Requires-Dist: numba>=0.61.2
Requires-Dist: numpy>=2.2.6
Requires-Dist: pandas>=2.3.1
Requires-Dist: py-vollib>=1.0.1
Requires-Dist: pyopengl>=3.1.9
Requires-Dist: pyopengl-accelerate>=3.1.9
Requires-Dist: pyqtgraph>=0.13.7
Requires-Dist: pyside6>=6.9.1
Requires-Dist: quantlib>=1.39
Requires-Dist: requests>=2.32.4
Requires-Dist: scipy>=1.16.1
Requires-Dist: websockets>=15.0.1
